wn_editor/__init__.py
wn_editor/editor.py
wn_editor/py.typed
wn_editor_extended-0.6.1.dist-info/licenses/LICENSE
wn_editor_extended-0.6.1.dist-info/WHEEL
wn_editor_extended-0.6.1.dist-info/METADATA
wn_editor_extended-0.6.1.dist-info/RECORD
