Metadata-Version: 2.4
Name: wn-editor-extended
Version: 0.6.1
Summary: An extended editor for wordnets, building on the popular 'wn' package with additional features for synset creation and relation management.
Keywords: wn,wordnet,editor,nlp,lexicon
Author-email: Salah Abdo <Salah.Abdo.Tech@gmail.com>
Requires-Python: >=3.9
Classifier: Intended Audience :: Information Technology
Classifier: Intended Audience :: Science/Research
Classifier: Operating System :: OS Independent
Classifier: Programming Language :: Python :: 3
Classifier: Programming Language :: Python
Classifier: Typing :: Typed
Classifier: Development Status :: 4 - Beta
Classifier: Environment :: Console
Classifier: Intended Audience :: Developers
Classifier: License :: OSI Approved :: MIT License
Classifier: Programming Language :: Python :: 3.9
Classifier: Programming Language :: Python :: 3.10
Classifier: Programming Language :: Python :: 3.11
Classifier: Programming Language :: Python :: 3.12
Classifier: Topic :: Scientific/Engineering :: Information Analysis
Classifier: Topic :: Software Development :: Libraries :: Python Modules
Classifier: Topic :: Text Processing :: Linguistic
License-File: LICENSE
Requires-Dist: wn>=0.9.1
Requires-Dist: pytest>=7.0.0 ; extra == "dev"
Requires-Dist: pytest-cov>=4.0.0 ; extra == "dev"
Project-URL: Homepage, https://github.com/Salah-Sal/wn-editor-extended
Project-URL: Issues, https://github.com/Salah-Sal/wn-editor-extended/issues
Project-URL: Repository, https://github.com/Salah-Sal/wn-editor-extended
Provides-Extra: dev
